<?xml version="1.0" encoding="UTF-8"?>
<plugins>
  <pyqgis_plugin name="Procesa Entrega IBD(Processing)" version="29/05/2024">
    <description>Procesamiento de imágenes de una entrega</description>
    <about>Descripción detallada del complemento</about>
    <version>29/05/2024</version>
    <qgis_minimum_version>3.0</qgis_minimum_version>
    <author_name>Jorge Parada</author_name>
    <download_url>https://github.com/JorgeParada4/plugins/blob/67e9f6dd3d4fe86c2811e35d703e1838dbbc539b/procesa_entrega_ibd_processing.zip</download_url>
  </pyqgis_plugin>
  <!-- Agrega más bloques <pyqgis_plugin> para otros complementos -->
</plugins>
